{"path":"/serie/stream/angel-sanctuary","name":"Angel Sanctuary","descr":"[Tenshi kinryoku] Der Junge Setsuna Mudo denkt die ganze Welt hätte sich gegen ihn verschworen, doch mit dem Himmel hat er nicht gerechnet. Genau von da droht ihm aber die größte Gefahr. Die aufrichtige Liebe zu seiner Schwester und seine verständnislose Mutter schwinden alsbald zu einem kleineren Problem. Denn die beiden Gestalten, die behaupten Dämonen zu sein, planen jemanden zu wecken, der in ihm wohnt - indem sie ihn töten.Weitere Verstrickungen mit Engeln erleichtern Setsunas Leben auch nicht wirklich. Katan versucht den \"anorganischen Engel\" Rosiel, Zwillingsbruder von Alexiel und einst mit ihr ranghöchster Engel im Himmel, aus seiner Verbannung zu befreien. Nur der hat anderes geplant, als wieder in den Himmel zurückzukehren. Auch er strebt an Alexiel wiederzuerwecken, denn er ist, ähnlich wie Setsuna, in seine Schwester verliebt.","seasons":[{"path":"/serie/stream/angel-sanctuary/staffel-1","seasonId":"Staffel 1","episodes":[{"path":"/serie/stream/angel-sanctuary/staffel-1/episode-1","name":"Folge 1","epNo":1,"alt":"Encounter","descr":"","versions":[{"languageKey":"1","streams":[{"path":"/redirect/12918382","hoster":"VOE"},{"path":"/redirect/8282302","hoster":"Streamtape"}]}]},{"path":"/serie/stream/angel-sanctuary/staffel-1/episode-2","name":"Folge 2","epNo":2,"alt":"Awakening","descr":"Setsuna findet heraus, dass seine Beziehung zu seiner Schwester öffentlich gemacht wurde und er ist bald erwacht.","versions":[{"languageKey":"1","streams":[{"path":"/redirect/8282311","hoster":"VOE"},{"path":"/redirect/8282312","hoster":"Streamtape"}]}]},{"path":"/serie/stream/angel-sanctuary/staffel-1/episode-3","name":"Folge 3","epNo":3,"alt":"Regeneration","descr":"Der letzte Kampf zwischen Himmel und Erde wird entfesselt. Können Setsuna und Sara überleben?","versions":[{"languageKey":"1","streams":[{"path":"/redirect/8282317","hoster":"VOE"},{"path":"/redirect/8282320","hoster":"Streamtape"}]}]}]}]}