{"seriesId":"big-mouth-2022","name":"Big Mouth (2022)","descr":"Thriller über einen erfolglosen Anwalt, der in einen Mordfall verwickelt wird und in die Rolle des genialen Betrügers Big Mouse gerät.","seasons":[{"seasonId":"staffel-1","episodes":[{"epId":"episode-1","name":"Folge 1","epNo":1,"alt":"Episode 1","descr":"Chang-ho, der kein Geld hat und kurz davor steht, seine Frau zu verlieren, erhält einen Anruf vom Bürgermeister von Gucheon.","versions":[{"lang":1,"streams":[{"redirect":12130588,"hoster":"VOE"},{"redirect":12130587,"hoster":"Doodstream"},{"redirect":12130594,"hoster":"Vidoza"},{"redirect":12130586,"hoster":"Streamtape"}]},{"lang":2,"streams":[{"redirect":12414309,"hoster":"VOE"},{"redirect":12414310,"hoster":"Streamtape"}]},{"lang":3,"streams":[{"redirect":11606192,"hoster":"VOE"},{"redirect":11606198,"hoster":"Streamtape"}]}]},{"epId":"episode-2","name":"Folge 2","epNo":2,"alt":"Episode 2","descr":"Chang-ho wird wegen Drogenmissbrauchs angeklagt und im Gucheon-Gefängnis eingesperrt. Aber warte, ist Chang-ho die große Maus?","versions":[{"lang":1,"streams":[{"redirect":12130591,"hoster":"VOE"},{"redirect":12130590,"hoster":"Doodstream"},{"redirect":12130592,"hoster":"Streamtape"}]},{"lang":2,"streams":[{"redirect":12414318,"hoster":"VOE"},{"redirect":12414320,"hoster":"Streamtape"}]},{"lang":3,"streams":[{"redirect":11606190,"hoster":"VOE"},{"redirect":11606195,"hoster":"Streamtape"}]}]},{"epId":"episode-3","name":"Folge 3","epNo":3,"alt":"Episode 3","descr":"Chang-ho muss seine Anerkennung als Big Mouse aufrechterhalten, um Mi-ho zu beschützen.","versions":[{"lang":1,"streams":[{"redirect":12130636,"hoster":"VOE"},{"redirect":12130639,"hoster":"Doodstream"},{"redirect":12130638,"hoster":"Streamtape"}]},{"lang":2,"streams":[{"redirect":12414314,"hoster":"VOE"},{"redirect":12414315,"hoster":"Streamtape"}]},{"lang":3,"streams":[{"redirect":12182565,"hoster":"VOE"},{"redirect":12182566,"hoster":"Streamtape"}]}]},{"epId":"episode-4","name":"Folge 4","epNo":4,"alt":"Episode 4","descr":"Gong Ji-hoon schließt eine Wette mit Chang-ho ab, um seine wahre Identität herauszufinden.","versions":[{"lang":1,"streams":[{"redirect":13916859,"hoster":"VOE"},{"redirect":12130642,"hoster":"Streamtape"}]},{"lang":2,"streams":[{"redirect":12414322,"hoster":"VOE"},{"redirect":12414323,"hoster":"Streamtape"}]},{"lang":3,"streams":[{"redirect":12182569,"hoster":"VOE"},{"redirect":12182585,"hoster":"Streamtape"}]}]},{"epId":"episode-5","name":"Folge 5","epNo":5,"alt":"Episode 5","descr":"Ji-hoon wendet sich an Mi-ho, um die These von Seo Jae-young zu finden. Kennt Mi-ho Chang-hos wahre Identität?","versions":[{"lang":1,"streams":[{"redirect":13090295,"hoster":"VOE"},{"redirect":12130647,"hoster":"Streamtape"}]},{"lang":2,"streams":[{"redirect":12414325,"hoster":"VOE"},{"redirect":12414327,"hoster":"Streamtape"}]},{"lang":3,"streams":[{"redirect":12182599,"hoster":"VOE"},{"redirect":12182612,"hoster":"Streamtape"}]}]},{"epId":"episode-6","name":"Folge 6","epNo":6,"alt":"Episode 6","descr":"Mi-ho schließt sich dem medizinischen Freiwilligenprogramm des Gefängnisses an, um Chang-ho zu treffen.","versions":[{"lang":1,"streams":[{"redirect":12919206,"hoster":"VOE"},{"redirect":12130617,"hoster":"Doodstream"},{"redirect":12130616,"hoster":"Streamtape"}]},{"lang":2,"streams":[{"redirect":12414469,"hoster":"VOE"},{"redirect":12414405,"hoster":"Streamtape"}]},{"lang":3,"streams":[{"redirect":12182625,"hoster":"VOE"},{"redirect":12182636,"hoster":"Streamtape"}]}]},{"epId":"episode-7","name":"Folge 7","epNo":7,"alt":"Episode 7","descr":"Jae-ho warnt Chang-ho, sich nicht mehr mit Seo Jae-youngs These zu befassen. Mi-ho wird plötzlich angegriffen.","versions":[{"lang":1,"streams":[{"redirect":12130615,"hoster":"VOE"},{"redirect":12130618,"hoster":"Streamtape"}]},{"lang":2,"streams":[{"redirect":12414377,"hoster":"VOE"},{"redirect":12414457,"hoster":"Streamtape"}]},{"lang":3,"streams":[{"redirect":12182651,"hoster":"VOE"},{"redirect":12182668,"hoster":"Streamtape"}]}]},{"epId":"episode-8","name":"Folge 8","epNo":8,"alt":"Episode 8","descr":"Chang-ho ist in einer psychiatrischen Klinik. Wird Chang-ho in der Lage sein, seine Identität in einem Zustand der Verwirrung zu verbergen?","versions":[{"lang":1,"streams":[{"redirect":12130626,"hoster":"VOE"},{"redirect":12130623,"hoster":"Streamtape"}]},{"lang":2,"streams":[{"redirect":12414509,"hoster":"VOE"},{"redirect":12414512,"hoster":"Streamtape"}]},{"lang":3,"streams":[{"redirect":12182698,"hoster":"VOE"},{"redirect":12182699,"hoster":"Streamtape"}]}]},{"epId":"episode-9","name":"Folge 9","epNo":9,"alt":"Episode 9","descr":"Chang-ho steht als Informant im Prozess gegen Seo Jae-young, und Jihoon und Jungrak suchen nach Chang-ho.","versions":[{"lang":1,"streams":[{"redirect":12130627,"hoster":"VOE"},{"redirect":12130625,"hoster":"Streamtape"}]},{"lang":2,"streams":[{"redirect":12414507,"hoster":"VOE"},{"redirect":12414506,"hoster":"Streamtape"}]},{"lang":3,"streams":[{"redirect":12182721,"hoster":"VOE"},{"redirect":12182734,"hoster":"Streamtape"}]}]},{"epId":"episode-10","name":"Folge 10","epNo":10,"alt":"Episode 10","descr":"Chang-ho bittet um ein Treffen mit Big Mouse und eine unerwartete Person taucht auf.","versions":[{"lang":1,"streams":[{"redirect":12130633,"hoster":"VOE"},{"redirect":12130631,"hoster":"Doodstream"},{"redirect":12130629,"hoster":"Streamtape"}]},{"lang":2,"streams":[{"redirect":12414516,"hoster":"VOE"},{"redirect":12414515,"hoster":"Streamtape"}]},{"lang":3,"streams":[{"redirect":12182752,"hoster":"VOE"},{"redirect":12182759,"hoster":"Streamtape"}]}]},{"epId":"episode-11","name":"Folge 11","epNo":11,"alt":"Episode 11","descr":"Changho verändert die Machtverhältnisse im Gefängnis und übt Druck auf Big Mouse aus. Doha stellt einen neuen Direktor ein.","versions":[{"lang":1,"streams":[{"redirect":13755141,"hoster":"VOE"},{"redirect":12130637,"hoster":"Doodstream"},{"redirect":12130635,"hoster":"Streamtape"}]},{"lang":2,"streams":[{"redirect":12414521,"hoster":"VOE"},{"redirect":12414520,"hoster":"Streamtape"}]},{"lang":3,"streams":[{"redirect":12182780,"hoster":"VOE"},{"redirect":12182801,"hoster":"Streamtape"}]}]},{"epId":"episode-12","name":"Folge 12","epNo":12,"alt":"Episode 12","descr":"Der Wärter plant, die Gefängnisaufstände zu nutzen, um Chang-ho und Mi-ho auszuschalten.","versions":[{"lang":1,"streams":[{"redirect":12183117,"hoster":"VOE"},{"redirect":12183119,"hoster":"Doodstream"},{"redirect":12183118,"hoster":"Streamtape"}]},{"lang":2,"streams":[{"redirect":12414525,"hoster":"VOE"},{"redirect":12414524,"hoster":"Streamtape"}]},{"lang":3,"streams":[{"redirect":12182563,"hoster":"VOE"},{"redirect":12182562,"hoster":"Streamtape"}]}]},{"epId":"episode-13","name":"Folge 13","epNo":13,"alt":"Episode 13","descr":"Das Kochplattenrestaurant liegt in Trümmern. Der aufgeregte Chang-ho trifft dort auf jemand Unerwartetes.","versions":[{"lang":1,"streams":[{"redirect":12213287,"hoster":"VOE"},{"redirect":12213293,"hoster":"Doodstream"},{"redirect":12213289,"hoster":"Streamtape"}]},{"lang":2,"streams":[{"redirect":12414528,"hoster":"VOE"},{"redirect":12414529,"hoster":"Streamtape"}]},{"lang":3,"streams":[{"redirect":12213343,"hoster":"VOE"},{"redirect":12213344,"hoster":"Streamtape"}]}]},{"epId":"episode-14","name":"Folge 14","epNo":14,"alt":"Episode 14","descr":"Chang-ho macht dem Vorsitzenden Kang ein verlockendes Angebot. Do-ha verschwört sich mit Yoon-gab, um Chang-ho loszuwerden.","versions":[{"lang":1,"streams":[{"redirect":12213292,"hoster":"VOE"},{"redirect":12213297,"hoster":"Streamtape"}]},{"lang":2,"streams":[{"redirect":12414533,"hoster":"VOE"},{"redirect":12414532,"hoster":"Streamtape"}]},{"lang":3,"streams":[{"redirect":12213345,"hoster":"VOE"},{"redirect":12213348,"hoster":"Streamtape"}]}]},{"epId":"episode-15","name":"Folge 15","epNo":15,"alt":"Episode 15","descr":"Chang-ho bereitet sich auf die vollwertigen Wahlen gegen Do-ha vor, aber Mi-hos Gesundheit ist in Schwierigkeiten.","versions":[{"lang":1,"streams":[{"redirect":12213458,"hoster":"VOE"},{"redirect":12213457,"hoster":"Streamtape"}]},{"lang":2,"streams":[{"redirect":12414536,"hoster":"VOE"},{"redirect":12414537,"hoster":"Streamtape"}]},{"lang":3,"streams":[{"redirect":12215457,"hoster":"VOE"},{"redirect":12215459,"hoster":"Streamtape"}]}]},{"epId":"episode-16","name":"Folge 16","epNo":16,"alt":"Episode 16","descr":"Die TV-Debatte beginnt und Mi-ho hat fast die rauchende Waffe, die Choi Do-ha zu Fall bringen wird.","versions":[{"lang":1,"streams":[{"redirect":12290615,"hoster":"VOE"},{"redirect":12290616,"hoster":"Streamtape"}]},{"lang":2,"streams":[{"redirect":12414542,"hoster":"VOE"},{"redirect":12414540,"hoster":"Streamtape"}]},{"lang":3,"streams":[{"redirect":12290618,"hoster":"VOE"},{"redirect":12290619,"hoster":"Streamtape"}]}]}]}]}