{"seriesId":"carnival-phantasm","name":"Carnival Phantasm","descr":"Anlässlich seines 10-jährigen Jubiläums hat das Studios TYPE-MOON mit Carnival Phantasm eine Animeumsetzung des Mangas \"Take Moon\" von Eri Takenashi herausgebracht, der die Helden aus Fate/stay night und Shingetsutan Tsukihime in eher untypischen Situationen zeigt. So wird aus dem Krieg um den heiligen Gral schnell mal ein Tennisturnier zwischen Caster und Berserker oder Arcueid kämpft als \"White-Moon-Princess PhantasMoon\" gegen das Böse.","seasons":[{"seasonId":"staffel-1","episodes":[{"epId":"episode-1","name":"","epNo":1,"alt":"The 5th Great Clash of the Magicians: The Holy Grail War","descr":"","versions":[{"lang":3,"streams":[{"redirect":8973452,"hoster":"VOE"},{"redirect":8339346,"hoster":"Streamtape"}]}]},{"epId":"episode-2","name":"","epNo":2,"alt":"Badump! Melty Blood","descr":"","versions":[{"lang":3,"streams":[{"redirect":8973454,"hoster":"VOE"},{"redirect":8339365,"hoster":"Streamtape"}]}]},{"epId":"episode-3","name":"","epNo":3,"alt":"It\u0027s a Daydream Everywhere","descr":"","versions":[{"lang":3,"streams":[{"redirect":8973460,"hoster":"VOE"},{"redirect":8339364,"hoster":"Streamtape"}]}]},{"epId":"episode-4","name":"","epNo":4,"alt":"Badump! Date Super Plan","descr":"","versions":[{"lang":3,"streams":[{"redirect":13504713,"hoster":"VOE"},{"redirect":8339361,"hoster":"Streamtape"}]}]},{"epId":"episode-5","name":"","epNo":5,"alt":"Berserker\u0027s First Errand","descr":"","versions":[{"lang":3,"streams":[{"redirect":13917003,"hoster":"VOE"},{"redirect":8339366,"hoster":"Streamtape"}]}]},{"epId":"episode-6","name":"","epNo":6,"alt":"Type-Moon Serial TV Novel Sakura","descr":"","versions":[{"lang":3,"streams":[{"redirect":13497443,"hoster":"VOE"},{"redirect":8339369,"hoster":"Streamtape"}]}]},{"epId":"episode-7","name":"","epNo":7,"alt":"An Expert Gift","descr":"","versions":[{"lang":3,"streams":[{"redirect":13531870,"hoster":"VOE"},{"redirect":12985446,"hoster":"Streamtape"}]}]},{"epId":"episode-8","name":"","epNo":8,"alt":"Saber at work","descr":"","versions":[{"lang":3,"streams":[{"redirect":8973463,"hoster":"VOE"},{"redirect":8339382,"hoster":"Streamtape"}]}]},{"epId":"episode-9","name":"","epNo":9,"alt":"Holy Grail Grand Prix","descr":"","versions":[{"lang":3,"streams":[{"redirect":8973465,"hoster":"VOE"},{"redirect":8339381,"hoster":"Streamtape"}]}]},{"epId":"episode-10","name":"","epNo":10,"alt":"Loli Reversion","descr":"","versions":[{"lang":3,"streams":[{"redirect":13497441,"hoster":"VOE"},{"redirect":8339383,"hoster":"Streamtape"}]}]},{"epId":"episode-11","name":"","epNo":11,"alt":"Final Dead Lancer","descr":"","versions":[{"lang":3,"streams":[{"redirect":13497444,"hoster":"VOE"},{"redirect":8339384,"hoster":"Streamtape"}]}]},{"epId":"episode-12","name":"","epNo":12,"alt":"Badump! Date Super Plan - Answer","descr":"","versions":[{"lang":3,"streams":[{"redirect":13531871,"hoster":"VOE"},{"redirect":8339396,"hoster":"Streamtape"}]}]}]}]}