{"seriesId":"chou-yuu-sekai-being-the-reality","name":"Chou Yuu Sekai: Being the Reality","descr":"Der Weltfrieden wird fortlaufend durch das Auftauchen mysteriöser Monster, der \"Disaster\" bedroht. Die Menschheit formte eine Spezialeinheit namens \"Saber\", um gegen die Monster zu kämpfen. Auch die mächtigen Industrieclans stellten eine von der Regierung unabhängige Verteidigungsorganisation auf die Beine, die sich mit schwankendem Erfolg Gefechte mit den Disastern liefert. Noii ist ein gewöhnlicher Oberschüler, der die Spezialeinheiten bewundert, die gegen die Disaster kämpfen. Doch mit dem Auftreten der mysteriösen Schulwechslerin Motis ändert sich sein alltägliches Leben vollständig. Realität und Virtualität, Spieler und NPC, Vater und Mutter … Wenn die Erinnerungen an die Zeit vor zehn Jahren klar werden, wird das Geheimnis der Welt gelüftet.","seasons":[{"seasonId":"staffel-1","episodes":[{"epId":"episode-1","name":"","epNo":1,"alt":"Episode 1","descr":"","versions":[{"lang":3,"streams":[{"redirect":8349013,"hoster":"VOE"},{"redirect":8349012,"hoster":"Streamtape"}]}]},{"epId":"episode-2","name":"","epNo":2,"alt":"Episode 2","descr":"","versions":[{"lang":3,"streams":[{"redirect":8349026,"hoster":"VOE"},{"redirect":8349027,"hoster":"Streamtape"}]}]},{"epId":"episode-3","name":"","epNo":3,"alt":"Episode 3","descr":"","versions":[{"lang":3,"streams":[{"redirect":8349020,"hoster":"VOE"},{"redirect":8349016,"hoster":"Streamtape"}]}]},{"epId":"episode-4","name":"","epNo":4,"alt":"Episode 4","descr":"","versions":[{"lang":3,"streams":[{"redirect":8349057,"hoster":"VOE"},{"redirect":8349081,"hoster":"Streamtape"}]}]},{"epId":"episode-5","name":"","epNo":5,"alt":"Episode 5","descr":"","versions":[{"lang":3,"streams":[{"redirect":12919976,"hoster":"VOE"},{"redirect":8349078,"hoster":"Streamtape"}]}]},{"epId":"episode-6","name":"","epNo":6,"alt":"Episode 6","descr":"","versions":[{"lang":3,"streams":[{"redirect":8349084,"hoster":"VOE"},{"redirect":8349087,"hoster":"Streamtape"}]}]}]}]}