{"seriesId":"danke-deutschland","name":"Danke Deutschland!","descr":"Die satirische Sketchshow. In der Comedy werden aktuelle, politische und gesellschaftskritische Themen in Sketchform verpackt. Es geht um das, was das Land aufregt, plagt und amüsiert.","seasons":[{"seasonId":"staffel-1","episodes":[{"epId":"episode-1","name":"Folge 1","epNo":1,"alt":"","descr":"","versions":[{"lang":1,"streams":[{"redirect":10018230,"hoster":"VOE"},{"redirect":10018231,"hoster":"Streamtape"}]}]},{"epId":"episode-2","name":"Folge 2","epNo":2,"alt":"","descr":"","versions":[{"lang":1,"streams":[{"redirect":10018234,"hoster":"VOE"},{"redirect":10018235,"hoster":"Streamtape"}]}]},{"epId":"episode-3","name":"Folge 3","epNo":3,"alt":"","descr":"","versions":[{"lang":1,"streams":[{"redirect":10018238,"hoster":"VOE"},{"redirect":10018236,"hoster":"Streamtape"}]}]},{"epId":"episode-4","name":"Folge 4","epNo":4,"alt":"","descr":"","versions":[{"lang":1,"streams":[{"redirect":13511375,"hoster":"VOE"},{"redirect":10018241,"hoster":"Streamtape"}]}]},{"epId":"episode-5","name":"Folge 5","epNo":5,"alt":"","descr":"","versions":[{"lang":1,"streams":[{"redirect":13511377,"hoster":"VOE"},{"redirect":10018245,"hoster":"Streamtape"}]}]},{"epId":"episode-6","name":"Folge 6","epNo":6,"alt":"","descr":"","versions":[{"lang":1,"streams":[{"redirect":13511382,"hoster":"VOE"},{"redirect":10018252,"hoster":"Streamtape"}]}]}]}]}